pyva/__init__.py
pyva/models.py
pyva/useful.py
pyva/coupling/__init__.py
pyva/coupling/connections.py
pyva/coupling/junctions.py
pyva/data/__init__.py
pyva/data/dof.py
pyva/data/matrixClasses.py
pyva/geometry/__init__.py
pyva/geometry/meshClasses.py
pyva/loads/__init__.py
pyva/loads/loadCase.py
pyva/properties/__init__.py
pyva/properties/geometricalPropertyClasses.py
pyva/properties/materialClasses.py
pyva/properties/structuralPropertyClasses.py
pyva/systems/SEA_system.py
pyva/systems/__init__.py
pyva/systems/acoustic1Dsystems.py
pyva/systems/acoustic3Dsystems.py
pyva/systems/acousticRadiators.py
pyva/systems/infiniteLayers.py
pyva/systems/lumpedSystems.py
pyva/systems/structure1Dsystems.py
pyva/systems/structure2Dsystems.py
pyva_toolbox-1.3.0.dist-info/LICENSE
pyva_toolbox-1.3.0.dist-info/METADATA
pyva_toolbox-1.3.0.dist-info/WHEEL
pyva_toolbox-1.3.0.dist-info/top_level.txt
pyva_toolbox-1.3.0.dist-info/RECORD
