Metadata-Version: 2.2
Name: pyva-toolbox
Version: 1.3.0
Summary: Python toolbox for vibroacoustic simulation
Author: Dr. Alexander Peiffer
Author-email: Alexander Peiffer <author@alexanderpeiffer.de>
Project-URL: Homepage, https://github.com/minipief/pyva
Project-URL: Bug Tracker, https://github.com/minipief/pyva/issues
Classifier: Programming Language :: Python :: 3
Classifier: License :: OSI Approved :: GNU Lesser General Public License v2 or later (LGPLv2+)
Classifier: Operating System :: OS Independent
Requires-Python: >=3.8
License-File: LICENSE
Requires-Dist: pint>=0.24.2
Requires-Dist: numpy>=2.1.3
Requires-Dist: matplotlib>=3.9.2
Requires-Dist: scipy>=1.14.1
Requires-Dist: pandas>=2.2.3
Dynamic: author
